{"success": true, "data": [{"user": {"id": 3, "name": "testuser"}, "challenge": {"category": "Cryptography", "id": 15, "value": 100, "name": "Base 16 (^16)"}, "id": 36, "team": null, "type": "correct", "challenge_id": 15, "date": "2025-10-15T12:30:28.758974+00:00"}, {"user": {"id": 3, "name": "testuser"}, "challenge": {"category": "OSINT", "id": 16, "value": 40, "name": "Old Compression, Older Mistakes"}, "id": 35, "team": null, "type": "correct", "challenge_id": 16, "date": "2025-10-15T12:26:55.819121+00:00"}, {"user": {"id": 3, "name": "testuser"}, "challenge": {"category": "Cryptography", "id": 14, "value": 30, "name": "Words Unlock"}, "id": 19, "team": null, "type": "correct", "challenge_id": 14, "date": "2025-10-12T21:47:06.757664+00:00"}, {"user": {"id": 3, "name": "testuser"}, "challenge": {"category": "Cryptography", "id": 13, "value": 20, "name": "Rotazione"}, "id": 18, "team": null, "type": "correct", "challenge_id": 13, "date": "2025-10-12T21:46:49.549970+00:00"}, {"user": {"id": 3, "name": "testuser"}, "challenge": {"category": "Image", "id": 5, "value": 20, "name": "Bees"}, "id": 12, "team": null, "type": "correct", "challenge_id": 5, "date": "2025-10-06T14:38:55.746723+00:00"}, {"user": {"id": 3, "name": "testuser"}, "challenge": {"category": "Web", "id": 3, "value": 30, "name": "Sneaky Robots"}, "id": 11, "team": null, "type": "correct", "challenge_id": 3, "date": "2025-09-24T14:39:52.528912+00:00"}, {"user": {"id": 3, "name": "testuser"}, "challenge": {"category": "Web", "id": 2, "value": 50, "name": "Robots"}, "id": 4, "team": null, "type": "correct", "challenge_id": 2, "date": "2025-09-22T18:28:56.205020+00:00"}, {"user": {"id": 3, "name": "testuser"}, "challenge": {"category": "", "id": 1, "value": 10, "name": "Hello, World!"}, "id": 3, "team": null, "type": "correct", "challenge_id": 1, "date": "2025-09-22T14:31:28.444429+00:00"}], "meta": {"count": 8}}
